pixiv_dl/__init__.py
pixiv_dl/__main__.py
pixiv_dl/config.py
pixiv_dl/downloader.py
pixiv_dl/filter.py
pixiv_dl-0.4.0.dist-info/entry_points.txt
pixiv_dl-0.4.0.dist-info/WHEEL
pixiv_dl-0.4.0.dist-info/METADATA
pixiv_dl-0.4.0.dist-info/RECORD
