Metadata-Version: 2.1
Name: pixiv-dl
Version: 0.4.0
Summary: A tool to download from pixiv
Home-page: https://github.com/Fuyukai/pixiv-dl
License: GPL-3.0-or-later
Author: Laura F Dickinson
Author-email: l@veriny.tf
Requires-Python: >=3.7,<4.0
Classifier: License :: OSI Approved :: GNU General Public License v3 or later (GPLv3+)
Classifier: Programming Language :: Python :: 3
Classifier: Programming Language :: Python :: 3.7
Provides-Extra: filter
Requires-Dist: arrow (>=0.15.2,<0.16.0)
Requires-Dist: jq (>=0.1.6,<0.2.0); extra == "filter"
Requires-Dist: pixivpy (>=3.5.0,<4.0.0)
Requires-Dist: termcolor (>=1.1.0,<2.0.0)
Requires-Dist: tomlkit (>=0.5.8,<0.6.0)
Project-URL: Repository, https://github.com/Fuyukai/pixiv-dl
